XRDimage/__init__.py
XRDimage/center_of_grav.py
XRDimage/dark_correction.py
XRDimage/ellipse_fitting.py
XRDimage/find_center.py
XRDimage/image_processing_function.py
XRDimage/image_registration.py
XRDimage/image_segmentation.py
XRDimage/mask.py
XRDimage/temperature_independent.py
XRDimage-0.0.1.7.dist-info/LICENSE
XRDimage-0.0.1.7.dist-info/METADATA
XRDimage-0.0.1.7.dist-info/WHEEL
XRDimage-0.0.1.7.dist-info/top_level.txt
XRDimage-0.0.1.7.dist-info/RECORD
