Metadata-Version: 2.1
Name: XRDimage
Version: 0.0.1.7
Summary: XRDImage is a Python 3 package developed by the SDLE Research Center at Case Western Reserve University in Cleveland, OH.
Home-page: http://engineering.case.edu/centers/sdle/
Author: Weiqi Yue, Ethan Fang, Gabriel Ponon, Zhuldyz Ualikhankyzy, Nathaniel K. Tomczak, Pawan K. Tripathi, Roger H. French
Author-email: wxy215@case.edu, pkt19@case.edu, roger.french@case.edu
License: MIT License
Project-URL: Documentation, https://xrdimage-doc.readthedocs.io/en/latest/
Project-URL: Bugtracker, https://bitbucket.org/cwrusdle/xrd-image/src/main/
Requires-Python: >=3.8
License-File: LICENSE
Requires-Dist: numpy
Requires-Dist: Pillow
Requires-Dist: opencv-python
Requires-Dist: matplotlib
Requires-Dist: imageio
Requires-Dist: scikit-learn
